fairmat_readers_transmission/__init__.py
fairmat_readers_transmission/_version.py
fairmat_readers_transmission/perkin_elmers_asc.py
fairmat_readers_transmission/readers.py
fairmat_readers_transmission-0.0.2.dist-info/LICENSE
fairmat_readers_transmission-0.0.2.dist-info/METADATA
fairmat_readers_transmission-0.0.2.dist-info/WHEEL
fairmat_readers_transmission-0.0.2.dist-info/top_level.txt
fairmat_readers_transmission-0.0.2.dist-info/RECORD
