Metadata-Version: 2.1
Name: fairmat-readers-transmission
Version: 0.0.2
Summary: A package containing file readers for transmission spectrophotometry raw files.
Author-email: Sarthak Kapoor <sarthak.kapoor@physik.hu-berlin.de>, Hampus Näsström <hampus.naesstroem@physik.hu-berlin.de>, Andrea Albino <andrea.albino@physik.hu-berlin.de>, Sebastian Brückner <sebastian.brueckner@ikz-berlin.de>
License: Apache License
Project-URL: Homepage, https://github.com/FAIRmat-NFDI/readers-transmission
Project-URL: Bug Tracker, https://github.com/FAIRmat-NFDI/readers-transmission/issues
Classifier: Programming Language :: Python :: 3
Classifier: Programming Language :: Python :: 3 :: Only
Classifier: Programming Language :: Python :: 3.9
Classifier: License :: OSI Approved :: Apache Software License
Requires-Python: >=3.8
License-File: LICENSE
Requires-Dist: numpy
Requires-Dist: pandas
Requires-Dist: pint
Provides-Extra: dev
Requires-Dist: pre-commit ; extra == 'dev'
Requires-Dist: pytest ; extra == 'dev'
Requires-Dist: ruff ; extra == 'dev'
Requires-Dist: structlog ; extra == 'dev'
